graphbrain/__init__.py
graphbrain/__main__.py
graphbrain/cli.py
graphbrain/colored.py
graphbrain/constants.py
graphbrain/hyperedge.cpython-39-darwin.so
graphbrain/hypergraph.py
graphbrain/logic.py
graphbrain/notebook.py
graphbrain/patterns.cpython-39-darwin.so
graphbrain/patterns.py
graphbrain/processor.py
graphbrain/corefs/__init__.py
graphbrain/corefs/names.py
graphbrain/corefs/onto.py
graphbrain/data/__init__.py
graphbrain/data/atoms-en.csv
graphbrain/meaning/__init__.py
graphbrain/meaning/case_generators.py
graphbrain/meaning/extractor.py
graphbrain/meaning/tests.py
graphbrain/memory/__init__.py
graphbrain/memory/leveldb.cpython-39-darwin.so
graphbrain/memory/permutations.cpython-39-darwin.so
graphbrain/memory/sqlite.cpython-39-darwin.so
graphbrain/parsers/__init__.py
graphbrain/parsers/alpha.cpython-39-darwin.so
graphbrain/parsers/alpha_beta.cpython-39-darwin.so
graphbrain/parsers/nlp.py
graphbrain/parsers/parser.py
graphbrain/parsers/parser_en.cpython-39-darwin.so
graphbrain/parsers/text.py
graphbrain/processors/__init__.py
graphbrain/processors/actors.py
graphbrain/processors/claims.py
graphbrain/processors/conflicts.py
graphbrain/processors/names.py
graphbrain/processors/number.py
graphbrain/processors/onto.py
graphbrain/processors/taxonomy.py
graphbrain/readers/__init__.py
graphbrain/readers/csv.py
graphbrain/readers/dir.py
graphbrain/readers/reader.py
graphbrain/readers/reddit.py
graphbrain/readers/txt.py
graphbrain/readers/wikipedia.py
graphbrain/tests/__init__.py
graphbrain/tests/test_corefs.py
graphbrain/tests/test_hyperedge.py
graphbrain/tests/test_hypergraph.py
graphbrain/tests/test_logic.py
graphbrain/tests/test_patterns.py
graphbrain/tests/test_permutations.py
graphbrain/utils/__init__.py
graphbrain/utils/concepts.py
graphbrain/utils/conjunctions.py
graphbrain/utils/corefs.py
graphbrain/utils/lemmas.py
graphbrain/utils/number.py
graphbrain/utils/ontology.py
scripts/__init__.py
scripts/extract-remaining-sentences.py
scripts/extract-sentences.py
graphbrain-0.6.1.dist-info/AUTHORS
graphbrain-0.6.1.dist-info/LICENSE
graphbrain-0.6.1.dist-info/METADATA
graphbrain-0.6.1.dist-info/WHEEL
graphbrain-0.6.1.dist-info/entry_points.txt
graphbrain-0.6.1.dist-info/top_level.txt
graphbrain-0.6.1.dist-info/RECORD
