Metadata-Version: 2.1
Name: graphbrain
Version: 0.6.1
Summary: Knowledge System + Natural Language Understanding
Home-page: http://graphbrain.net
Author: Telmo Menezes et al.
Author-email: telmo@telmomenezes.net
License: MIT
Keywords: NLP,AI,Knowledge Representation,Knowledge Systems,Natural Language Understanding,Text Analysis,Cognition
Classifier: Development Status :: 4 - Beta
Classifier: Programming Language :: Python :: 3
Classifier: License :: OSI Approved :: MIT License
Classifier: Operating System :: OS Independent
Classifier: Environment :: Console
Classifier: Intended Audience :: Science/Research
Classifier: Topic :: Scientific/Engineering :: Artificial Intelligence
Classifier: Topic :: Scientific/Engineering :: Information Analysis
Classifier: Topic :: Sociology
Requires-Python: >=3.6
License-File: LICENSE
License-File: AUTHORS
Requires-Dist: asciitree
Requires-Dist: ipython
Requires-Dist: mwparserfromhell
Requires-Dist: networkx
Requires-Dist: numpy
Requires-Dist: plyvel
Requires-Dist: progressbar2
Requires-Dist: scikit-learn
Requires-Dist: spacy
Requires-Dist: termcolor
Provides-Extra: dev
Requires-Dist: cython (>=0.25) ; extra == 'dev'
Requires-Dist: pytest ; extra == 'dev'
Requires-Dist: Sphinx ; extra == 'dev'
Requires-Dist: sphinx-rtd-theme ; extra == 'dev'
